fystool/__about__.py
fystool/__init__.py
fystool/__main__.py
fystool-0.0.2.dist-info/METADATA
fystool-0.0.2.dist-info/WHEEL
fystool-0.0.2.dist-info/entry_points.txt
fystool-0.0.2.dist-info/licenses/LICENSE.txt
fystool-0.0.2.dist-info/RECORD
